bci_dataset/__init__.py
bci_dataset/hdf_controller.py
bci_dataset/importer.py
bci_dataset/test_hdf_controller.py
bci_dataset/test_importer.py
bci_dataset/test_updater_class.py
bci_dataset/updater.py
bci_dataset-1.0.0.dist-info/LICENSE
bci_dataset-1.0.0.dist-info/METADATA
bci_dataset-1.0.0.dist-info/WHEEL
bci_dataset-1.0.0.dist-info/top_level.txt
bci_dataset-1.0.0.dist-info/RECORD
