Metadata-Version: 2.1
Name: bci-dataset
Version: 1.0.0
Summary: Building HDF datasets for machine learning.
Home-page: https://github.com/s-n-1-0/bci-dataset
Download-URL: https://github.com/s-n-1-0/bci-dataset
Author: sn-10
License: MIT
Keywords: eeg
License-File: LICENSE
Requires-Dist: numpy (>=1.22.4)
Requires-Dist: h5py (>=3.7.0)
Requires-Dist: mne[hdf5] (>=1.3.0)
